django_uv/__init__.py
django_uv-0.3.0.dist-info/WHEEL
django_uv-0.3.0.dist-info/entry_points.txt
django_uv-0.3.0.dist-info/METADATA
django_uv-0.3.0.dist-info/RECORD
