Metadata-Version: 2.3
Name: django-uv
Version: 0.3.0
Summary: Add your description here
Author: Paul Traylor
Author-email: Paul Traylor <kungfudiscomonkey@gmail.com>
Requires-Dist: django>=5.2.5
Requires-Python: >=3.13
